runs.py
runs/__init__.py
runs/commands.py
runs/main.py
runs/util.py
tf_run_manager-2.1.6.dist-info/DESCRIPTION.rst
tf_run_manager-2.1.6.dist-info/METADATA
tf_run_manager-2.1.6.dist-info/RECORD
tf_run_manager-2.1.6.dist-info/WHEEL
tf_run_manager-2.1.6.dist-info/entry_points.txt
tf_run_manager-2.1.6.dist-info/metadata.json
tf_run_manager-2.1.6.dist-info/top_level.txt
