Metadata-Version: 2.0
Name: tf-run-manager
Version: 2.1.6
Summary: A utility for tracking and reproducing Tensorflow runs.
Home-page: https://github.com/lobachevzky/tf-run-manager
Author: Ethan Brooks
Author-email: ethanbrooks@gmail.com
License: MIT
Keywords: tensorflow utilities development
Platform: UNKNOWN
Classifier: Development Status :: 3 - Alpha
Classifier: Intended Audience :: Developers
Classifier: Topic :: Scientific/Engineering :: Artificial Intelligence
Classifier: License :: OSI Approved :: MIT License
Classifier: Programming Language :: Python :: 2
Classifier: Programming Language :: Python :: 3
Requires-Dist: paramiko (==2.3.1)
Requires-Dist: termcolor (==1.1.0)
Requires-Dist: PyYAML (==3.12)
Requires-Dist: tabulate (==0.8.1)
